aiooncue/__init__.py
aiooncue/const.py
aiooncue/py.typed
aiooncue-0.3.9.dist-info/AUTHORS.rst
aiooncue-0.3.9.dist-info/LICENSE
aiooncue-0.3.9.dist-info/METADATA
aiooncue-0.3.9.dist-info/WHEEL
aiooncue-0.3.9.dist-info/top_level.txt
aiooncue-0.3.9.dist-info/RECORD
