Metadata-Version: 2.2
Name: aiooncue
Version: 0.3.9
Summary: Async for Oncue
Author-email: "J. Nick Koston" <nick@koston.org>
License: Apache-2.0
Project-URL: Homepage, https://github.com/bdraco/aiooncue
Keywords: aiooncue
Classifier: Development Status :: 2 - Pre-Alpha
Classifier: Intended Audience :: Developers
Classifier: License :: OSI Approved :: Apache Software License
Classifier: Natural Language :: English
Classifier: Programming Language :: Python :: 3
Classifier: Programming Language :: Python :: 3.5
Classifier: Programming Language :: Python :: 3.6
Classifier: Programming Language :: Python :: 3.7
Classifier: Programming Language :: Python :: 3.8
Requires-Python: >=3.5
License-File: LICENSE
License-File: AUTHORS.rst
Requires-Dist: aiohttp
